gemini_wt/__init__.py
gemini_wt/cli.py
gemini_wt-0.1.3.dist-info/METADATA
gemini_wt-0.1.3.dist-info/WHEEL
gemini_wt-0.1.3.dist-info/entry_points.txt
gemini_wt-0.1.3.dist-info/RECORD
