Metadata-Version: 2.4
Name: gemini-wt
Version: 0.1.3
Summary: Manage parallel Gemini CLI instances
Project-URL: Homepage, https://github.com/Danielratmiroff/gemini-wt
Author: Daniel Ratmiroff
Keywords: ai,gemini,git
Classifier: Development Status :: 4 - Beta
Classifier: Intended Audience :: Developers
Classifier: Programming Language :: Python :: 3
Requires-Python: >=3.12
Requires-Dist: cyclopts>=3.0.0
Requires-Dist: rich>=13.0.0
